lammps_logfile/File.py
lammps_logfile/__init__.py
lammps_logfile/cmd_interface.py
lammps_logfile/utils.py
tests/__init__.py
tests/test_File.py
atomify_lammps_logfile-1.0.2.dist-info/LICENSE
atomify_lammps_logfile-1.0.2.dist-info/METADATA
atomify_lammps_logfile-1.0.2.dist-info/WHEEL
atomify_lammps_logfile-1.0.2.dist-info/entry_points.txt
atomify_lammps_logfile-1.0.2.dist-info/top_level.txt
atomify_lammps_logfile-1.0.2.dist-info/RECORD
