Metadata-Version: 2.1
Name: atomify-lammps-logfile
Version: 1.0.2
Summary: Tool to read lammps log files into python data structure
Home-page: http://github.com/henriasv/lammps-logfile
Author: Henrik Andersen Sveinsson
Author-email: henrik.sveinsson@me.com
License: GNU GPL v3.0
License-File: LICENSE
Requires-Dist: pandas
Requires-Dist: numpy
Requires-Dist: matplotlib
